Workbook

Sheet 📖 Instrucciones
B2: 📖 Guía de Uso — Calculadora de Ahorro GTC
B3: Global Talent Connections · www.globaltalent-connections.com
B6: 🟦 CÓMO USAR ESTA CALCULADORA
B8: Paso 1 — Ir a la hoja '🧮 Calculadora'
B9: Introduce el número de trabajadores que quieres comparar en la celda C10.
B11: Paso 2 — Rellenar los costes de España (columna C, celdas azules)
B12: Introduce el salario bruto anual y otros costes de tu equipo actual. Los valores preestablecidos son medias del mercado español 2024-2025.
B14: Paso 3 — Ajustar los costes GTC (columna F, celdas azules)
B15: Los valores de GTC ya están pre-rellenados con datos reales orientativos. Puedes ajustarlos si tienes una propuesta personalizada.
B17: Paso 4 — Ver tu ahorro
B18: El resumen ejecutivo al final de la hoja calcula automáticamente el ahorro total, el % de reducción de costes y el ahorro mensual.
B20: Paso 5 — Consultar el gráfico
... B36: 📍 Alicante, España

Sheet 🧮 Calculadora
B2: 💼 Calculadora de Ahorro Global Talent Connections | J2: 📈 Comparativa Visual de Costes — Calculadora GTC
B3: Compara el coste real de tu equipo actual vs. contratar con nosotros en Global Talent Connections | J3: Los datos se actualizan automáticamente desde la hoja Calculadora
B4: 📝 Introduce tus datos en las celdas azules · Los resultados se calculan automáticamente
B6: SECCIÓN 1 — DATOS DE TU EMPRESA | J6: Concepto | K6: España (€) | L6: GTC LATAM (€) | M6: Ahorro (€)
B7: Nombre de tu empresa (opcional) | C7: STYLO | J7: Coste por trabajador | K7: ='🧮 Calculadora'!C25 -> 28160 | L7: ='🧮 Calculadora'!F25 -> 20300 | M7: =K7-L7 -> 7860
B8: Sector / Industria | C8: Ejemplo: marketing | G8: Solicitar un Asistente | J8: Coste total equipo | K8: ='🧮 Calculadora'!D25 -> 56320 | L8: ='🧮 Calculadora'!G25 -> 40600 | M8: =K8-L8 -> 15720
B9: Salario mensual | C9: 1000 | J9: Ahorro anual | K9: ='🧮 Calculadora'!D25-'🧮 Calculadora'!G25 -> 15720
B10: Número de trabajadores a comparar | C10: 2 | D10: nº de personas de tu equipo actual
B11: Seniority | C11: Senior
B13: 🇪🇸 TRABAJADOR EN ESPAÑA | F13: 🌎 TALENTO GTC (LATAM)
B14: Concepto | C14: Coste / Trabajador (€) | D14: Coste Total Equipo (€) | F14: Coste / Trabajador (€) | G14: Coste Total Equipo (€)
B15: Salario bruto anual (12 pagas) | C15: =C9*12 -> 12000 | D15: =C15*C10 -> 24000 | F15: =IF(C11="Junior",1300*12,IF(C11="Mid",1400*12,IF(C11="Senior",1650*12,0))) -> 19800 | G15: =F15*C10 -> 39600
B16: Seguridad Social empresa (~33%) | C16: =C15*33% -> 3960 | D16: =C16*C10 -> 7920 | F16: 0 | G16: =F16*C10 -> 0
B17: Bonus / variable anual | C17: 2000 | D17: =C17*C10 -> 4000 | F17: 0 | G17: =F17*C10 -> 0
B18: Equipamiento (laptop, móvil, etc.) | C18: 1200 | D18: =C18*C10 -> 2400 | F18: 0 | G18: =F18*C10 -> 0
B19: Espacio oficina / puesto de trabajo | C19: 3600 | D19: =C19*C10 -> 7200 | F19: 0 | G19: =F19*C10 -> 0
B20: Formación y desarrollo | C20: 800 | D20: =C20*C10 -> 1600 | F20: 0 | G20: =F20*C10 -> 0
B21: Software / licencias por empleado | C21: 500 | D21: =C21*C10 -> 1000 | F21: =C21 -> 500 | G21: =F21*C10 -> 1000
B22: Gestión HR / reclutamiento (amortizado) | C22: 1500 | D22: =C22*C10 -> 3000 | F22: 0 | G22: =F22*C10 -> 0
B23: Costes de desvinculación / rotación | C23: 2000 | D23: =C23*C10 -> 4000 | F23: 0 | G23: =F23*C10 -> 0
B24: Otros costes (transporte, dietas, etc.) | C24: 600 | D24: =C24*C10 -> 1200 | F24: 0 | G24: =F24*C10 -> 0
B25: COSTE TOTAL ANUAL POR EMPLEADO / EQUIPO | C25: =SUM(C15:C24) -> 28160 | D25: =SUM(D15:D24) -> 56320 | F25: =SUM(F15:F24) -> 20300 | G25: =SUM(G15:G24) -> 40600
B27: 📊 RESUMEN EJECUTIVO — ¿CUÁNTO PUEDES AHORRAR?
B28: Coste total anual equipo en España | C28: =D25 -> 56320 | F28: ℹ Coste con trabajadores locales en España
B29: Coste total anual equipo con GTC (LATAM) | C29: =G25 -> 40600 | F29: ℹ Profesionales de LATAM vía GTC
B30: 💰 Ahorro total anual | C30: =D25-G25 -> 15720 | F30: ℹ Ahorro directo en tu cuenta bancaria | J30: 🏆 TU RESUMEN DE AHORRO
B31: 📉 Porcentaje de ahorro | C31: =IF(D25>0,(D25-G25)/D25,0) -> 0.27911932 | F31: ℹ Porcentaje de tu presupuesto que recuperas | J31: AHORRO MENSUAL | K31: % DE AHORRO | M31: AHORRO TOTAL ANUAL
B32: 📅 Ahorro mensual estimado | C32: =(D25-G25)/12 -> 1310 | F32: ℹ Liquidez mensual adicional para tu empresa | J32: =('🧮 Calculadora'!D25-'🧮 Calculadora'!G25)/12 -> 1310 | K32: =IF('🧮 Calculadora'!D25>0,('🧮 Calculadora'!D25-'🧮 Calculadora'!G25)/'🧮 Calculadora'!D25,0) -> 0.27911932 | M32: ='🧮 Calculadora'!D25-'🧮 Calculadora'!G25 -> 15720
B33: 🔄 Periodo de retorno de la inversión | C33: =IF((D25-G25)>0,"Inmediato — ahorro desde el día 1","Revisar datos") -> Inmediato — ahorro desde el día 1 | F33: ℹ El ahorro comienza desde la primera nómina | J33: Resultados en base a los datos introducidos en la hoja 🧮 Calculadora · globaltalent-connections.com
B35: 🎯 CONCLUSIÓN PERSONALIZADA
B36: ="Con un equipo de "&C10&" personas, tu empresa gasta "&TEXT(D25,"#,##0")&"€/año en España. Con GTC, ese coste bajaría a "&TEXT(G25,"#,##0")&"€ — un ahorro de "&TEXT(D25-G25,"#,##0")&"€ anuales ("&TEXT(IF(D25>0,(D25-G25)/D25,0),"0.0%")&") sin renunciar a la calidad del talento." -> Con un equipo de 2 personas, tu empresa gasta 56,320€/año en España. Con GTC, ese coste bajaría a 40,600€ — un ahorro de 15,720€ anuales (27.9%) sin renunciar a la calidad del talento.
B39: ¿Listo para dar el siguiente paso? Escríbenos y revisemos juntos los perfiles que tu empresa necesita.
B40: 🌐www.globaltalent-connections.com/ | 📧 info@globaltalent-connections.com | 💬 WhatsApp: +34 689 53 98 96
